CHANGES.txt
LICENSE.txt
MANIFEST.in
README.md
setup.py
django_leaderboard/__init__.py
django_leaderboard/forms.py
django_leaderboard/models.py
django_leaderboard/tests.py
django_leaderboard/urls.py
django_leaderboard/views.py
django_leaderboard.egg-info/PKG-INFO
django_leaderboard.egg-info/SOURCES.txt
django_leaderboard.egg-info/dependency_links.txt
django_leaderboard.egg-info/not-zip-safe
django_leaderboard.egg-info/top_level.txt
django_leaderboard/templates/django_leaderboard/highscores.html