Metadata-Version: 1.0
Name: django-leaderboard
Version: 0.1.0
Summary: A Django leaderboard (scoreboard) app, using redis as its backend
Home-page: https://github.com/laplacesdemon/django-leaderboard
Author: Suleyman Melikoglu
Author-email: suleyman@melikoglu.info
License: BSD licence, see LICENCE.txt
Platform: UNKNOWN
